{
  "MetaData": {
    "ContentFormatVersion": 4,
    "Id": "ChronoShift",
    "Name": "ChronoShift",
    "ResourcePath": "ChronoShift.inibin"
  },
  "Values": {
    "SpellData": {
      "SubjectToGlobalCooldown": 1,
      "HitEffectName": "ChronoRefresh_tar.troy",
      "Effect3Level5Amount": 0,
      "Effect2Level0Amount": 0,
      "BelongsToAvatar": "0",
      "HavePointEffect": "0",
      "Effect1Level1Amount": "600.0000",
      "TriggersGlobalCooldown": 1,
      "Level2Desc": "Level 2",
      "Coefficient": "2.0000",
      "Effect3Level4Amount": 0,
      "Effect2Level5Amount": 0,
      "HitBoneName": "head",
      "CastRadius": "300.0000",
      "Effect1Level0Amount": 0,
      "AfterEffectName": "ChronoRefresh_tar.troy",
      "MissileSpeed": "20.0000",
      "Effect3Level3Amount": 0,
      "AnimationName": "Spell3",
      "IsDisabledWhileDead": 1,
      "Effect2Level4Amount": 0,
      "DisplayName": "game_spell_displayname_ChronoShift",
      "TextFlags": "Instacast | AffectFriends | AffectHeroes",
      "Level3Desc": "Level 3",
      "Effect1Level5Amount": 0,
      "InventoryIcon": "Chronokeeper_Timetwister.dds",
      "CantCancelWhileChanneling": "0",
      "PointEffectName": "",
      "CastTargetAdditionalUnitsRadius": 0,
      "HaveAfterEffect": "0",
      "Sound_CastName": "Minotaur_Pulverize.wav",
      "MissileBoneName": "R_hand",
      "HaveHitEffect": "0",
      "CastConeAngle": "45.0000",
      "Effect3Level2Amount": 0,
      "LineMissileBounces": "0",
      "Effect2Level3Amount": "7.0000",
      "SelectionPreference": "friend",
      "Cooldown1": "180.0000",
      "Cooldown2": "180.0000",
      "Cooldown3": "180.0000",
      "Cooldown4": 0,
      "Cooldown5": 0,
      "DynamicTooltip": "game_spell_tooltip_ChronoShift",
      "TargettingType": 1,
      "Effect1Level4Amount": 0,
      "MissileEffect": "AnnieBasicAttack_mis.troy",
      "DeathRecapPriority": "0",
      "CastConeDistance": "100.0000",
      "Sound_HitName": "none.wav",
      "LineWidth": 0,
      "DelayCastOffsetPercent": "0.03660",
      "Level4Desc": "Level 4",
      "Effect3Level1Amount": 0,
      "Flags": 67588,
      "CantCancelWhileWindingUp": 1,
      "DelayTotalTimePercent": "-0.48750",
      "Effect2Level2Amount": "7.0000",
      "CastFrame": "12.90500",
      "DynamicExtended": "game_spell_levelup_ChronoShift",
      "Effect1Level3Amount": "1100.0000",
      "Description": "game_spell_description_ChronoShift",
      "HaveHitBone": 1,
      "AnimationLoopName": "",
      "IsToggleSpell": "0",
      "ApplyAttackDamage": "0",
      "Effect3Level0Amount": 0,
      "ManaCost1": "200.0000",
      "ManaCost2": "200.0000",
      "ManaCost3": "200.0000",
      "CastRange": "900.0000",
      "StartCooldown": 0,
      "Level1Desc": "Level 1",
      "Effect2Level1Amount": "7.0000",
      "Version": 1,
      "AnimationWinddownName": "",
      "BounceRadius": "450.0000",
      "Effect1Level2Amount": "850.0000",
      "Level5Desc": "Level 5",
      "CastType": "0"
    }
  }
}
